mm_strk/__init__.py
mm_strk/account.py
mm_strk/balance.py
mm_strk/domain.py
mm_strk/py.typed
mm_strk/cli/__init__.py
mm_strk/cli/cli.py
mm_strk/cli/cli_utils.py
mm_strk/cli/commands/__init__.py
mm_strk/cli/commands/node.py
mm_strk-0.4.3.dist-info/METADATA
mm_strk-0.4.3.dist-info/WHEEL
mm_strk-0.4.3.dist-info/entry_points.txt
mm_strk-0.4.3.dist-info/RECORD
