Metadata-Version: 2.4
Name: mm-strk
Version: 0.4.3
Requires-Python: >=3.13
Requires-Dist: mm-web3~=0.5.7
Requires-Dist: starknet-py~=0.29.0
Requires-Dist: typer~=0.21.1
